<Properties StartupConfiguration="{9B638C86-5C94-4969-9485-C57A38833C4B}|Default">
  <MonoDevelop.Ide.ItemProperties.HelloWorld PreferredExecutionTarget="MonoDevelop.Default" />
  <MonoDevelop.Ide.Workbench ActiveDocument="Controllers/ValuesController.cs">
    <Files>
      <File FileName="Controllers/ValuesController.cs" Line="17" Column="1" />
    </Files>
  </MonoDevelop.Ide.Workbench>
  <MonoDevelop.Ide.Workspace ActiveConfiguration="Debug" />
  <MonoDevelop.Ide.DebuggingService.Breakpoints>
    <BreakpointStore>
      <Breakpoint file="/Users/andrew/code/dotnet/projects/HelloWorld/Controllers/ValuesController.cs" relfile="Controllers/ValuesController.cs" line="17" column="1" />
    </BreakpointStore>
  </MonoDevelop.Ide.DebuggingService.Breakpoints>
  <MonoDevelop.Ide.DebuggingService.PinnedWatches />
  <MultiItemStartupConfigurations />
</Properties>